cloudzipfile/__init__.py
cloudzipfile/cloudzipfile.py
cloudzipfile/cloudclients/__init__.py
cloudzipfile/cloudclients/cloudclients.py
cloudzipfile-1.0.5.dist-info/LICENSE
cloudzipfile-1.0.5.dist-info/WHEEL
cloudzipfile-1.0.5.dist-info/METADATA
cloudzipfile-1.0.5.dist-info/RECORD
