Metadata-Version: 2.1
Name: cloudzipfile
Version: 1.0.5
Summary: Use cloud-stored zipfiles with full ZipFile functionality, including partial downloads. 
Author-email: Jesse Wursten <jessaius+cloudzipfile@hotmail.com>
Requires-Python: >=3.0
Classifier: License :: OSI Approved :: MIT License
Requires-Dist: azure-storage-blob
Requires-Dist: flit ; extra == "dev"
Requires-Dist: pytest ; extra == "dev"
Project-URL: Source, https://github.com/Danferno/cloudzipfile
Provides-Extra: dev
